{
  "mission_id": "MISSION_0065",
  "site_id": "SITE_KOL_006",
  "total_anomaly_frames": 71,
  "annotations": [
    {
      "frame_id": 630,
      "timestamp_utc": "2024-04-04T17:20:03.000Z",
      "mission_id": "MISSION_0065",
      "site_id": "SITE_KOL_006",
      "anomaly_class": "structural_crack",
      "confidence": 0.901,
      "bbox_xywh": [
        209,
        102,
        30,
        119
      ],
      "gps": {
        "lat": 22.5726379,
        "lon": 88.3639161,
        "alt_m": 27.35
      },
      "ir_temp_delta_c": 5.6,
      "inspection_phase": "antenna_inspection",
      "drone_alt_m": 45.6,
      "distance_to_tower_m": 3.47
    },
    {
      "frame_id": 631,
      "timestamp_utc": "2024-04-04T17:20:03.100Z",
      "mission_id": "MISSION_0065",
      "site_id": "SITE_KOL_006",
      "anomaly_class": "structural_crack",
      "confidence": 0.929,
      "bbox_xywh": [
        209,
        102,
        30,
        119
      ],
      "gps": {
        "lat": 22.5726379,
        "lon": 88.3639161,
        "alt_m": 27.35
      },
      "ir_temp_delta_c": 6.7,
      "inspection_phase": "antenna_inspection",
      "drone_alt_m": 45.62,
      "distance_to_tower_m": 3.53
    },
    {
      "frame_id": 632,
      "timestamp_utc": "2024-04-04T17:20:03.200Z",
      "mission_id": "MISSION_0065",
      "site_id": "SITE_KOL_006",
      "anomaly_class": "structural_crack",
      "confidence": 0.934,
      "bbox_xywh": [
        209,
        102,
        30,
        119
      ],
      "gps": {
        "lat": 22.5726379,
        "lon": 88.3639161,
        "alt_m": 27.35
      },
      "ir_temp_delta_c": 6.3,
      "inspection_phase": "antenna_inspection",
      "drone_alt_m": 45.61,
      "distance_to_tower_m": 3.44
    },
    {
      "frame_id": 633,
      "timestamp_utc": "2024-04-04T17:20:03.300Z",
      "mission_id": "MISSION_0065",
      "site_id": "SITE_KOL_006",
      "anomaly_class": "structural_crack",
      "confidence": 0.901,
      "bbox_xywh": [
        209,
        102,
        30,
        119
      ],
      "gps": {
        "lat": 22.5726379,
        "lon": 88.3639161,
        "alt_m": 27.35
      },
      "ir_temp_delta_c": 7.0,
      "inspection_phase": "antenna_inspection",
      "drone_alt_m": 45.67,
      "distance_to_tower_m": 3.87
    },
    {
      "frame_id": 634,
      "timestamp_utc": "2024-04-04T17:20:03.400Z",
      "mission_id": "MISSION_0065",
      "site_id": "SITE_KOL_006",
      "anomaly_class": "structural_crack",
      "confidence": 0.878,
      "bbox_xywh": [
        209,
        102,
        30,
        119
      ],
      "gps": {
        "lat": 22.5726379,
        "lon": 88.3639161,
        "alt_m": 27.35
      },
      "ir_temp_delta_c": 8.1,
      "inspection_phase": "antenna_inspection",
      "drone_alt_m": 45.66,
      "distance_to_tower_m": 3.39
    },
    {
      "frame_id": 635,
      "timestamp_utc": "2024-04-04T17:20:03.500Z",
      "mission_id": "MISSION_0065",
      "site_id": "SITE_KOL_006",
      "anomaly_class": "structural_crack",
      "confidence": 0.918,
      "bbox_xywh": [
        209,
        102,
        30,
        119
      ],
      "gps": {
        "lat": 22.5726379,
        "lon": 88.3639161,
        "alt_m": 27.35
      },
      "ir_temp_delta_c": 5.3,
      "inspection_phase": "antenna_inspection",
      "drone_alt_m": 45.65,
      "distance_to_tower_m": 4.29
    },
    {
      "frame_id": 636,
      "timestamp_utc": "2024-04-04T17:20:03.600Z",
      "mission_id": "MISSION_0065",
      "site_id": "SITE_KOL_006",
      "anomaly_class": "structural_crack",
      "confidence": 0.952,
      "bbox_xywh": [
        209,
        102,
        30,
        119
      ],
      "gps": {
        "lat": 22.5726379,
        "lon": 88.3639161,
        "alt_m": 27.35
      },
      "ir_temp_delta_c": 7.8,
      "inspection_phase": "antenna_inspection",
      "drone_alt_m": 45.6,
      "distance_to_tower_m": 4.52
    },
    {
      "frame_id": 637,
      "timestamp_utc": "2024-04-04T17:20:03.700Z",
      "mission_id": "MISSION_0065",
      "site_id": "SITE_KOL_006",
      "anomaly_class": "structural_crack",
      "confidence": 0.903,
      "bbox_xywh": [
        209,
        102,
        30,
        119
      ],
      "gps": {
        "lat": 22.5726379,
        "lon": 88.3639161,
        "alt_m": 27.35
      },
      "ir_temp_delta_c": 6.1,
      "inspection_phase": "antenna_inspection",
      "drone_alt_m": 45.57,
      "distance_to_tower_m": 4.74
    },
    {
      "frame_id": 638,
      "timestamp_utc": "2024-04-04T17:20:03.800Z",
      "mission_id": "MISSION_0065",
      "site_id": "SITE_KOL_006",
      "anomaly_class": "structural_crack",
      "confidence": 0.963,
      "bbox_xywh": [
        209,
        102,
        30,
        119
      ],
      "gps": {
        "lat": 22.5726379,
        "lon": 88.3639161,
        "alt_m": 27.35
      },
      "ir_temp_delta_c": 4.9,
      "inspection_phase": "antenna_inspection",
      "drone_alt_m": 45.55,
      "distance_to_tower_m": 5.14
    },
    {
      "frame_id": 639,
      "timestamp_utc": "2024-04-04T17:20:03.900Z",
      "mission_id": "MISSION_0065",
      "site_id": "SITE_KOL_006",
      "anomaly_class": "structural_crack",
      "confidence": 0.919,
      "bbox_xywh": [
        209,
        102,
        30,
        119
      ],
      "gps": {
        "lat": 22.5726379,
        "lon": 88.3639161,
        "alt_m": 27.35
      },
      "ir_temp_delta_c": 8.2,
      "inspection_phase": "antenna_inspection",
      "drone_alt_m": 45.58,
      "distance_to_tower_m": 5.47
    },
    {
      "frame_id": 640,
      "timestamp_utc": "2024-04-04T17:20:04.000Z",
      "mission_id": "MISSION_0065",
      "site_id": "SITE_KOL_006",
      "anomaly_class": "structural_crack",
      "confidence": 0.929,
      "bbox_xywh": [
        209,
        102,
        30,
        119
      ],
      "gps": {
        "lat": 22.5726379,
        "lon": 88.3639161,
        "alt_m": 27.35
      },
      "ir_temp_delta_c": 8.3,
      "inspection_phase": "antenna_inspection",
      "drone_alt_m": 45.63,
      "distance_to_tower_m": 6.0
    },
    {
      "frame_id": 641,
      "timestamp_utc": "2024-04-04T17:20:04.100Z",
      "mission_id": "MISSION_0065",
      "site_id": "SITE_KOL_006",
      "anomaly_class": "structural_crack",
      "confidence": 0.957,
      "bbox_xywh": [
        209,
        102,
        30,
        119
      ],
      "gps": {
        "lat": 22.5726379,
        "lon": 88.3639161,
        "alt_m": 27.35
      },
      "ir_temp_delta_c": 8.2,
      "inspection_phase": "antenna_inspection",
      "drone_alt_m": 45.61,
      "distance_to_tower_m": 6.09
    },
    {
      "frame_id": 642,
      "timestamp_utc": "2024-04-04T17:20:04.200Z",
      "mission_id": "MISSION_0065",
      "site_id": "SITE_KOL_006",
      "anomaly_class": "structural_crack",
      "confidence": 0.866,
      "bbox_xywh": [
        209,
        102,
        30,
        119
      ],
      "gps": {
        "lat": 22.5726379,
        "lon": 88.3639161,
        "alt_m": 27.35
      },
      "ir_temp_delta_c": 8.3,
      "inspection_phase": "antenna_inspection",
      "drone_alt_m": 45.54,
      "distance_to_tower_m": 6.08
    },
    {
      "frame_id": 643,
      "timestamp_utc": "2024-04-04T17:20:04.300Z",
      "mission_id": "MISSION_0065",
      "site_id": "SITE_KOL_006",
      "anomaly_class": "structural_crack",
      "confidence": 0.893,
      "bbox_xywh": [
        209,
        102,
        30,
        119
      ],
      "gps": {
        "lat": 22.5726379,
        "lon": 88.3639161,
        "alt_m": 27.35
      },
      "ir_temp_delta_c": 6.7,
      "inspection_phase": "antenna_inspection",
      "drone_alt_m": 45.58,
      "distance_to_tower_m": 6.51
    },
    {
      "frame_id": 644,
      "timestamp_utc": "2024-04-04T17:20:04.400Z",
      "mission_id": "MISSION_0065",
      "site_id": "SITE_KOL_006",
      "anomaly_class": "structural_crack",
      "confidence": 0.896,
      "bbox_xywh": [
        209,
        102,
        30,
        119
      ],
      "gps": {
        "lat": 22.5726379,
        "lon": 88.3639161,
        "alt_m": 27.35
      },
      "ir_temp_delta_c": 8.0,
      "inspection_phase": "antenna_inspection",
      "drone_alt_m": 45.58,
      "distance_to_tower_m": 6.39
    },
    {
      "frame_id": 645,
      "timestamp_utc": "2024-04-04T17:20:04.500Z",
      "mission_id": "MISSION_0065",
      "site_id": "SITE_KOL_006",
      "anomaly_class": "structural_crack",
      "confidence": 0.926,
      "bbox_xywh": [
        209,
        102,
        30,
        119
      ],
      "gps": {
        "lat": 22.5726379,
        "lon": 88.3639161,
        "alt_m": 27.35
      },
      "ir_temp_delta_c": 9.7,
      "inspection_phase": "antenna_inspection",
      "drone_alt_m": 45.63,
      "distance_to_tower_m": 5.72
    },
    {
      "frame_id": 646,
      "timestamp_utc": "2024-04-04T17:20:04.600Z",
      "mission_id": "MISSION_0065",
      "site_id": "SITE_KOL_006",
      "anomaly_class": "structural_crack",
      "confidence": 0.927,
      "bbox_xywh": [
        209,
        102,
        30,
        119
      ],
      "gps": {
        "lat": 22.5726379,
        "lon": 88.3639161,
        "alt_m": 27.35
      },
      "ir_temp_delta_c": 6.2,
      "inspection_phase": "antenna_inspection",
      "drone_alt_m": 45.61,
      "distance_to_tower_m": 5.81
    },
    {
      "frame_id": 647,
      "timestamp_utc": "2024-04-04T17:20:04.700Z",
      "mission_id": "MISSION_0065",
      "site_id": "SITE_KOL_006",
      "anomaly_class": "structural_crack",
      "confidence": 0.903,
      "bbox_xywh": [
        209,
        102,
        30,
        119
      ],
      "gps": {
        "lat": 22.5726379,
        "lon": 88.3639161,
        "alt_m": 27.35
      },
      "ir_temp_delta_c": 8.8,
      "inspection_phase": "antenna_inspection",
      "drone_alt_m": 45.52,
      "distance_to_tower_m": 5.96
    },
    {
      "frame_id": 648,
      "timestamp_utc": "2024-04-04T17:20:04.800Z",
      "mission_id": "MISSION_0065",
      "site_id": "SITE_KOL_006",
      "anomaly_class": "structural_crack",
      "confidence": 0.929,
      "bbox_xywh": [
        209,
        102,
        30,
        119
      ],
      "gps": {
        "lat": 22.5726379,
        "lon": 88.3639161,
        "alt_m": 27.35
      },
      "ir_temp_delta_c": 8.9,
      "inspection_phase": "antenna_inspection",
      "drone_alt_m": 45.47,
      "distance_to_tower_m": 5.84
    },
    {
      "frame_id": 649,
      "timestamp_utc": "2024-04-04T17:20:04.900Z",
      "mission_id": "MISSION_0065",
      "site_id": "SITE_KOL_006",
      "anomaly_class": "structural_crack",
      "confidence": 0.893,
      "bbox_xywh": [
        209,
        102,
        30,
        119
      ],
      "gps": {
        "lat": 22.5726379,
        "lon": 88.3639161,
        "alt_m": 27.35
      },
      "ir_temp_delta_c": 4.4,
      "inspection_phase": "antenna_inspection",
      "drone_alt_m": 45.56,
      "distance_to_tower_m": 5.56
    },
    {
      "frame_id": 650,
      "timestamp_utc": "2024-04-04T17:20:05.000Z",
      "mission_id": "MISSION_0065",
      "site_id": "SITE_KOL_006",
      "anomaly_class": "structural_crack",
      "confidence": 0.937,
      "bbox_xywh": [
        209,
        102,
        30,
        119
      ],
      "gps": {
        "lat": 22.5726379,
        "lon": 88.3639161,
        "alt_m": 27.35
      },
      "ir_temp_delta_c": 7.3,
      "inspection_phase": "antenna_inspection",
      "drone_alt_m": 45.48,
      "distance_to_tower_m": 5.31
    },
    {
      "frame_id": 651,
      "timestamp_utc": "2024-04-04T17:20:05.100Z",
      "mission_id": "MISSION_0065",
      "site_id": "SITE_KOL_006",
      "anomaly_class": "structural_crack",
      "confidence": 0.944,
      "bbox_xywh": [
        209,
        102,
        30,
        119
      ],
      "gps": {
        "lat": 22.5726379,
        "lon": 88.3639161,
        "alt_m": 27.35
      },
      "ir_temp_delta_c": 10.0,
      "inspection_phase": "antenna_inspection",
      "drone_alt_m": 45.37,
      "distance_to_tower_m": 5.61
    },
    {
      "frame_id": 652,
      "timestamp_utc": "2024-04-04T17:20:05.200Z",
      "mission_id": "MISSION_0065",
      "site_id": "SITE_KOL_006",
      "anomaly_class": "structural_crack",
      "confidence": 0.966,
      "bbox_xywh": [
        209,
        102,
        30,
        119
      ],
      "gps": {
        "lat": 22.5726379,
        "lon": 88.3639161,
        "alt_m": 27.35
      },
      "ir_temp_delta_c": 8.6,
      "inspection_phase": "antenna_inspection",
      "drone_alt_m": 45.44,
      "distance_to_tower_m": 5.92
    },
    {
      "frame_id": 653,
      "timestamp_utc": "2024-04-04T17:20:05.300Z",
      "mission_id": "MISSION_0065",
      "site_id": "SITE_KOL_006",
      "anomaly_class": "structural_crack",
      "confidence": 0.929,
      "bbox_xywh": [
        209,
        102,
        30,
        119
      ],
      "gps": {
        "lat": 22.5726379,
        "lon": 88.3639161,
        "alt_m": 27.35
      },
      "ir_temp_delta_c": 9.2,
      "inspection_phase": "antenna_inspection",
      "drone_alt_m": 45.5,
      "distance_to_tower_m": 5.72
    },
    {
      "frame_id": 654,
      "timestamp_utc": "2024-04-04T17:20:05.400Z",
      "mission_id": "MISSION_0065",
      "site_id": "SITE_KOL_006",
      "anomaly_class": "structural_crack",
      "confidence": 0.962,
      "bbox_xywh": [
        209,
        102,
        30,
        119
      ],
      "gps": {
        "lat": 22.5726379,
        "lon": 88.3639161,
        "alt_m": 27.35
      },
      "ir_temp_delta_c": 9.6,
      "inspection_phase": "antenna_inspection",
      "drone_alt_m": 45.52,
      "distance_to_tower_m": 5.44
    },
    {
      "frame_id": 655,
      "timestamp_utc": "2024-04-04T17:20:05.500Z",
      "mission_id": "MISSION_0065",
      "site_id": "SITE_KOL_006",
      "anomaly_class": "structural_crack",
      "confidence": 0.908,
      "bbox_xywh": [
        209,
        102,
        30,
        119
      ],
      "gps": {
        "lat": 22.5726379,
        "lon": 88.3639161,
        "alt_m": 27.35
      },
      "ir_temp_delta_c": 6.8,
      "inspection_phase": "antenna_inspection",
      "drone_alt_m": 45.52,
      "distance_to_tower_m": 5.4
    },
    {
      "frame_id": 656,
      "timestamp_utc": "2024-04-04T17:20:05.600Z",
      "mission_id": "MISSION_0065",
      "site_id": "SITE_KOL_006",
      "anomaly_class": "structural_crack",
      "confidence": 0.929,
      "bbox_xywh": [
        209,
        102,
        30,
        119
      ],
      "gps": {
        "lat": 22.5726379,
        "lon": 88.3639161,
        "alt_m": 27.35
      },
      "ir_temp_delta_c": 7.7,
      "inspection_phase": "antenna_inspection",
      "drone_alt_m": 45.53,
      "distance_to_tower_m": 5.84
    },
    {
      "frame_id": 657,
      "timestamp_utc": "2024-04-04T17:20:05.700Z",
      "mission_id": "MISSION_0065",
      "site_id": "SITE_KOL_006",
      "anomaly_class": "structural_crack",
      "confidence": 0.926,
      "bbox_xywh": [
        209,
        102,
        30,
        119
      ],
      "gps": {
        "lat": 22.5726379,
        "lon": 88.3639161,
        "alt_m": 27.35
      },
      "ir_temp_delta_c": 9.7,
      "inspection_phase": "antenna_inspection",
      "drone_alt_m": 45.61,
      "distance_to_tower_m": 5.73
    },
    {
      "frame_id": 658,
      "timestamp_utc": "2024-04-04T17:20:05.800Z",
      "mission_id": "MISSION_0065",
      "site_id": "SITE_KOL_006",
      "anomaly_class": "structural_crack",
      "confidence": 0.894,
      "bbox_xywh": [
        209,
        102,
        30,
        119
      ],
      "gps": {
        "lat": 22.5726379,
        "lon": 88.3639161,
        "alt_m": 27.35
      },
      "ir_temp_delta_c": 8.2,
      "inspection_phase": "antenna_inspection",
      "drone_alt_m": 45.57,
      "distance_to_tower_m": 5.19
    },
    {
      "frame_id": 659,
      "timestamp_utc": "2024-04-04T17:20:05.900Z",
      "mission_id": "MISSION_0065",
      "site_id": "SITE_KOL_006",
      "anomaly_class": "structural_crack",
      "confidence": 0.875,
      "bbox_xywh": [
        209,
        102,
        30,
        119
      ],
      "gps": {
        "lat": 22.5726379,
        "lon": 88.3639161,
        "alt_m": 27.35
      },
      "ir_temp_delta_c": 7.1,
      "inspection_phase": "antenna_inspection",
      "drone_alt_m": 45.56,
      "distance_to_tower_m": 4.75
    },
    {
      "frame_id": 660,
      "timestamp_utc": "2024-04-04T17:20:06.000Z",
      "mission_id": "MISSION_0065",
      "site_id": "SITE_KOL_006",
      "anomaly_class": "structural_crack",
      "confidence": 0.911,
      "bbox_xywh": [
        209,
        102,
        30,
        119
      ],
      "gps": {
        "lat": 22.5726379,
        "lon": 88.3639161,
        "alt_m": 27.35
      },
      "ir_temp_delta_c": 9.2,
      "inspection_phase": "antenna_inspection",
      "drone_alt_m": 45.53,
      "distance_to_tower_m": 5.36
    },
    {
      "frame_id": 661,
      "timestamp_utc": "2024-04-04T17:20:06.100Z",
      "mission_id": "MISSION_0065",
      "site_id": "SITE_KOL_006",
      "anomaly_class": "structural_crack",
      "confidence": 0.922,
      "bbox_xywh": [
        209,
        102,
        30,
        119
      ],
      "gps": {
        "lat": 22.5726379,
        "lon": 88.3639161,
        "alt_m": 27.35
      },
      "ir_temp_delta_c": 8.2,
      "inspection_phase": "antenna_inspection",
      "drone_alt_m": 45.52,
      "distance_to_tower_m": 5.17
    },
    {
      "frame_id": 662,
      "timestamp_utc": "2024-04-04T17:20:06.200Z",
      "mission_id": "MISSION_0065",
      "site_id": "SITE_KOL_006",
      "anomaly_class": "structural_crack",
      "confidence": 0.905,
      "bbox_xywh": [
        209,
        102,
        30,
        119
      ],
      "gps": {
        "lat": 22.5726379,
        "lon": 88.3639161,
        "alt_m": 27.35
      },
      "ir_temp_delta_c": 5.5,
      "inspection_phase": "antenna_inspection",
      "drone_alt_m": 45.43,
      "distance_to_tower_m": 5.62
    },
    {
      "frame_id": 663,
      "timestamp_utc": "2024-04-04T17:20:06.300Z",
      "mission_id": "MISSION_0065",
      "site_id": "SITE_KOL_006",
      "anomaly_class": "structural_crack",
      "confidence": 0.89,
      "bbox_xywh": [
        209,
        102,
        30,
        119
      ],
      "gps": {
        "lat": 22.5726379,
        "lon": 88.3639161,
        "alt_m": 27.35
      },
      "ir_temp_delta_c": 7.2,
      "inspection_phase": "antenna_inspection",
      "drone_alt_m": 45.52,
      "distance_to_tower_m": 5.47
    },
    {
      "frame_id": 664,
      "timestamp_utc": "2024-04-04T17:20:06.400Z",
      "mission_id": "MISSION_0065",
      "site_id": "SITE_KOL_006",
      "anomaly_class": "structural_crack",
      "confidence": 0.868,
      "bbox_xywh": [
        209,
        102,
        30,
        119
      ],
      "gps": {
        "lat": 22.5726379,
        "lon": 88.3639161,
        "alt_m": 27.35
      },
      "ir_temp_delta_c": 5.5,
      "inspection_phase": "antenna_inspection",
      "drone_alt_m": 45.58,
      "distance_to_tower_m": 5.44
    },
    {
      "frame_id": 665,
      "timestamp_utc": "2024-04-04T17:20:06.500Z",
      "mission_id": "MISSION_0065",
      "site_id": "SITE_KOL_006",
      "anomaly_class": "structural_crack",
      "confidence": 0.928,
      "bbox_xywh": [
        209,
        102,
        30,
        119
      ],
      "gps": {
        "lat": 22.5726379,
        "lon": 88.3639161,
        "alt_m": 27.35
      },
      "ir_temp_delta_c": 5.6,
      "inspection_phase": "antenna_inspection",
      "drone_alt_m": 45.58,
      "distance_to_tower_m": 5.51
    },
    {
      "frame_id": 666,
      "timestamp_utc": "2024-04-04T17:20:06.600Z",
      "mission_id": "MISSION_0065",
      "site_id": "SITE_KOL_006",
      "anomaly_class": "structural_crack",
      "confidence": 0.874,
      "bbox_xywh": [
        209,
        102,
        30,
        119
      ],
      "gps": {
        "lat": 22.5726379,
        "lon": 88.3639161,
        "alt_m": 27.35
      },
      "ir_temp_delta_c": 5.9,
      "inspection_phase": "antenna_inspection",
      "drone_alt_m": 45.61,
      "distance_to_tower_m": 5.09
    },
    {
      "frame_id": 667,
      "timestamp_utc": "2024-04-04T17:20:06.700Z",
      "mission_id": "MISSION_0065",
      "site_id": "SITE_KOL_006",
      "anomaly_class": "structural_crack",
      "confidence": 0.92,
      "bbox_xywh": [
        209,
        102,
        30,
        119
      ],
      "gps": {
        "lat": 22.5726379,
        "lon": 88.3639161,
        "alt_m": 27.35
      },
      "ir_temp_delta_c": 8.8,
      "inspection_phase": "antenna_inspection",
      "drone_alt_m": 45.57,
      "distance_to_tower_m": 5.59
    },
    {
      "frame_id": 668,
      "timestamp_utc": "2024-04-04T17:20:06.800Z",
      "mission_id": "MISSION_0065",
      "site_id": "SITE_KOL_006",
      "anomaly_class": "structural_crack",
      "confidence": 0.913,
      "bbox_xywh": [
        209,
        102,
        30,
        119
      ],
      "gps": {
        "lat": 22.5726379,
        "lon": 88.3639161,
        "alt_m": 27.35
      },
      "ir_temp_delta_c": 9.0,
      "inspection_phase": "antenna_inspection",
      "drone_alt_m": 45.6,
      "distance_to_tower_m": 4.94
    },
    {
      "frame_id": 669,
      "timestamp_utc": "2024-04-04T17:20:06.900Z",
      "mission_id": "MISSION_0065",
      "site_id": "SITE_KOL_006",
      "anomaly_class": "structural_crack",
      "confidence": 0.923,
      "bbox_xywh": [
        209,
        102,
        30,
        119
      ],
      "gps": {
        "lat": 22.5726379,
        "lon": 88.3639161,
        "alt_m": 27.35
      },
      "ir_temp_delta_c": 11.1,
      "inspection_phase": "antenna_inspection",
      "drone_alt_m": 45.64,
      "distance_to_tower_m": 4.59
    },
    {
      "frame_id": 670,
      "timestamp_utc": "2024-04-04T17:20:07.000Z",
      "mission_id": "MISSION_0065",
      "site_id": "SITE_KOL_006",
      "anomaly_class": "structural_crack",
      "confidence": 0.893,
      "bbox_xywh": [
        209,
        102,
        30,
        119
      ],
      "gps": {
        "lat": 22.5726379,
        "lon": 88.3639161,
        "alt_m": 27.35
      },
      "ir_temp_delta_c": 9.2,
      "inspection_phase": "antenna_inspection",
      "drone_alt_m": 45.66,
      "distance_to_tower_m": 4.55
    },
    {
      "frame_id": 671,
      "timestamp_utc": "2024-04-04T17:20:07.100Z",
      "mission_id": "MISSION_0065",
      "site_id": "SITE_KOL_006",
      "anomaly_class": "structural_crack",
      "confidence": 0.861,
      "bbox_xywh": [
        209,
        102,
        30,
        119
      ],
      "gps": {
        "lat": 22.5726379,
        "lon": 88.3639161,
        "alt_m": 27.35
      },
      "ir_temp_delta_c": 6.3,
      "inspection_phase": "antenna_inspection",
      "drone_alt_m": 45.77,
      "distance_to_tower_m": 4.02
    },
    {
      "frame_id": 672,
      "timestamp_utc": "2024-04-04T17:20:07.200Z",
      "mission_id": "MISSION_0065",
      "site_id": "SITE_KOL_006",
      "anomaly_class": "structural_crack",
      "confidence": 0.868,
      "bbox_xywh": [
        209,
        102,
        30,
        119
      ],
      "gps": {
        "lat": 22.5726379,
        "lon": 88.3639161,
        "alt_m": 27.35
      },
      "ir_temp_delta_c": 8.1,
      "inspection_phase": "antenna_inspection",
      "drone_alt_m": 45.77,
      "distance_to_tower_m": 4.19
    },
    {
      "frame_id": 673,
      "timestamp_utc": "2024-04-04T17:20:07.300Z",
      "mission_id": "MISSION_0065",
      "site_id": "SITE_KOL_006",
      "anomaly_class": "structural_crack",
      "confidence": 0.865,
      "bbox_xywh": [
        209,
        102,
        30,
        119
      ],
      "gps": {
        "lat": 22.5726379,
        "lon": 88.3639161,
        "alt_m": 27.35
      },
      "ir_temp_delta_c": 6.3,
      "inspection_phase": "antenna_inspection",
      "drone_alt_m": 45.76,
      "distance_to_tower_m": 4.49
    },
    {
      "frame_id": 674,
      "timestamp_utc": "2024-04-04T17:20:07.400Z",
      "mission_id": "MISSION_0065",
      "site_id": "SITE_KOL_006",
      "anomaly_class": "structural_crack",
      "confidence": 0.943,
      "bbox_xywh": [
        209,
        102,
        30,
        119
      ],
      "gps": {
        "lat": 22.5726379,
        "lon": 88.3639161,
        "alt_m": 27.35
      },
      "ir_temp_delta_c": 5.3,
      "inspection_phase": "antenna_inspection",
      "drone_alt_m": 45.84,
      "distance_to_tower_m": 4.46
    },
    {
      "frame_id": 675,
      "timestamp_utc": "2024-04-04T17:20:07.500Z",
      "mission_id": "MISSION_0065",
      "site_id": "SITE_KOL_006",
      "anomaly_class": "structural_crack",
      "confidence": 0.926,
      "bbox_xywh": [
        209,
        102,
        30,
        119
      ],
      "gps": {
        "lat": 22.5726379,
        "lon": 88.3639161,
        "alt_m": 27.35
      },
      "ir_temp_delta_c": 6.9,
      "inspection_phase": "antenna_inspection",
      "drone_alt_m": 45.81,
      "distance_to_tower_m": 4.43
    },
    {
      "frame_id": 676,
      "timestamp_utc": "2024-04-04T17:20:07.600Z",
      "mission_id": "MISSION_0065",
      "site_id": "SITE_KOL_006",
      "anomaly_class": "structural_crack",
      "confidence": 0.904,
      "bbox_xywh": [
        209,
        102,
        30,
        119
      ],
      "gps": {
        "lat": 22.5726379,
        "lon": 88.3639161,
        "alt_m": 27.35
      },
      "ir_temp_delta_c": 5.4,
      "inspection_phase": "antenna_inspection",
      "drone_alt_m": 45.73,
      "distance_to_tower_m": 3.76
    },
    {
      "frame_id": 677,
      "timestamp_utc": "2024-04-04T17:20:07.700Z",
      "mission_id": "MISSION_0065",
      "site_id": "SITE_KOL_006",
      "anomaly_class": "structural_crack",
      "confidence": 0.921,
      "bbox_xywh": [
        209,
        102,
        30,
        119
      ],
      "gps": {
        "lat": 22.5726379,
        "lon": 88.3639161,
        "alt_m": 27.35
      },
      "ir_temp_delta_c": 5.8,
      "inspection_phase": "antenna_inspection",
      "drone_alt_m": 45.82,
      "distance_to_tower_m": 3.68
    },
    {
      "frame_id": 678,
      "timestamp_utc": "2024-04-04T17:20:07.800Z",
      "mission_id": "MISSION_0065",
      "site_id": "SITE_KOL_006",
      "anomaly_class": "structural_crack",
      "confidence": 0.93,
      "bbox_xywh": [
        209,
        102,
        30,
        119
      ],
      "gps": {
        "lat": 22.5726379,
        "lon": 88.3639161,
        "alt_m": 27.35
      },
      "ir_temp_delta_c": 7.0,
      "inspection_phase": "antenna_inspection",
      "drone_alt_m": 45.8,
      "distance_to_tower_m": 3.84
    },
    {
      "frame_id": 679,
      "timestamp_utc": "2024-04-04T17:20:07.900Z",
      "mission_id": "MISSION_0065",
      "site_id": "SITE_KOL_006",
      "anomaly_class": "structural_crack",
      "confidence": 0.9,
      "bbox_xywh": [
        209,
        102,
        30,
        119
      ],
      "gps": {
        "lat": 22.5726379,
        "lon": 88.3639161,
        "alt_m": 27.35
      },
      "ir_temp_delta_c": 5.7,
      "inspection_phase": "antenna_inspection",
      "drone_alt_m": 45.79,
      "distance_to_tower_m": 3.75
    },
    {
      "frame_id": 680,
      "timestamp_utc": "2024-04-04T17:20:08.000Z",
      "mission_id": "MISSION_0065",
      "site_id": "SITE_KOL_006",
      "anomaly_class": "structural_crack",
      "confidence": 0.903,
      "bbox_xywh": [
        209,
        102,
        30,
        119
      ],
      "gps": {
        "lat": 22.5726379,
        "lon": 88.3639161,
        "alt_m": 27.35
      },
      "ir_temp_delta_c": 7.4,
      "inspection_phase": "antenna_inspection",
      "drone_alt_m": 45.81,
      "distance_to_tower_m": 3.49
    },
    {
      "frame_id": 681,
      "timestamp_utc": "2024-04-04T17:20:08.100Z",
      "mission_id": "MISSION_0065",
      "site_id": "SITE_KOL_006",
      "anomaly_class": "structural_crack",
      "confidence": 0.943,
      "bbox_xywh": [
        209,
        102,
        30,
        119
      ],
      "gps": {
        "lat": 22.5726379,
        "lon": 88.3639161,
        "alt_m": 27.35
      },
      "ir_temp_delta_c": 4.4,
      "inspection_phase": "antenna_inspection",
      "drone_alt_m": 45.8,
      "distance_to_tower_m": 3.78
    },
    {
      "frame_id": 682,
      "timestamp_utc": "2024-04-04T17:20:08.200Z",
      "mission_id": "MISSION_0065",
      "site_id": "SITE_KOL_006",
      "anomaly_class": "structural_crack",
      "confidence": 0.912,
      "bbox_xywh": [
        209,
        102,
        30,
        119
      ],
      "gps": {
        "lat": 22.5726379,
        "lon": 88.3639161,
        "alt_m": 27.35
      },
      "ir_temp_delta_c": 6.3,
      "inspection_phase": "antenna_inspection",
      "drone_alt_m": 45.76,
      "distance_to_tower_m": 3.99
    },
    {
      "frame_id": 683,
      "timestamp_utc": "2024-04-04T17:20:08.300Z",
      "mission_id": "MISSION_0065",
      "site_id": "SITE_KOL_006",
      "anomaly_class": "structural_crack",
      "confidence": 0.896,
      "bbox_xywh": [
        209,
        102,
        30,
        119
      ],
      "gps": {
        "lat": 22.5726379,
        "lon": 88.3639161,
        "alt_m": 27.35
      },
      "ir_temp_delta_c": 7.7,
      "inspection_phase": "antenna_inspection",
      "drone_alt_m": 45.71,
      "distance_to_tower_m": 3.68
    },
    {
      "frame_id": 684,
      "timestamp_utc": "2024-04-04T17:20:08.400Z",
      "mission_id": "MISSION_0065",
      "site_id": "SITE_KOL_006",
      "anomaly_class": "structural_crack",
      "confidence": 0.88,
      "bbox_xywh": [
        209,
        102,
        30,
        119
      ],
      "gps": {
        "lat": 22.5726379,
        "lon": 88.3639161,
        "alt_m": 27.35
      },
      "ir_temp_delta_c": 9.4,
      "inspection_phase": "antenna_inspection",
      "drone_alt_m": 45.78,
      "distance_to_tower_m": 4.07
    },
    {
      "frame_id": 685,
      "timestamp_utc": "2024-04-04T17:20:08.500Z",
      "mission_id": "MISSION_0065",
      "site_id": "SITE_KOL_006",
      "anomaly_class": "structural_crack",
      "confidence": 0.912,
      "bbox_xywh": [
        209,
        102,
        30,
        119
      ],
      "gps": {
        "lat": 22.5726379,
        "lon": 88.3639161,
        "alt_m": 27.35
      },
      "ir_temp_delta_c": 7.9,
      "inspection_phase": "antenna_inspection",
      "drone_alt_m": 45.75,
      "distance_to_tower_m": 3.86
    },
    {
      "frame_id": 686,
      "timestamp_utc": "2024-04-04T17:20:08.600Z",
      "mission_id": "MISSION_0065",
      "site_id": "SITE_KOL_006",
      "anomaly_class": "structural_crack",
      "confidence": 0.895,
      "bbox_xywh": [
        209,
        102,
        30,
        119
      ],
      "gps": {
        "lat": 22.5726379,
        "lon": 88.3639161,
        "alt_m": 27.35
      },
      "ir_temp_delta_c": 4.9,
      "inspection_phase": "antenna_inspection",
      "drone_alt_m": 45.69,
      "distance_to_tower_m": 4.26
    },
    {
      "frame_id": 687,
      "timestamp_utc": "2024-04-04T17:20:08.700Z",
      "mission_id": "MISSION_0065",
      "site_id": "SITE_KOL_006",
      "anomaly_class": "structural_crack",
      "confidence": 0.971,
      "bbox_xywh": [
        209,
        102,
        30,
        119
      ],
      "gps": {
        "lat": 22.5726379,
        "lon": 88.3639161,
        "alt_m": 27.35
      },
      "ir_temp_delta_c": 8.2,
      "inspection_phase": "antenna_inspection",
      "drone_alt_m": 45.69,
      "distance_to_tower_m": 4.36
    },
    {
      "frame_id": 688,
      "timestamp_utc": "2024-04-04T17:20:08.800Z",
      "mission_id": "MISSION_0065",
      "site_id": "SITE_KOL_006",
      "anomaly_class": "structural_crack",
      "confidence": 0.884,
      "bbox_xywh": [
        209,
        102,
        30,
        119
      ],
      "gps": {
        "lat": 22.5726379,
        "lon": 88.3639161,
        "alt_m": 27.35
      },
      "ir_temp_delta_c": 5.2,
      "inspection_phase": "antenna_inspection",
      "drone_alt_m": 45.7,
      "distance_to_tower_m": 4.13
    },
    {
      "frame_id": 689,
      "timestamp_utc": "2024-04-04T17:20:08.900Z",
      "mission_id": "MISSION_0065",
      "site_id": "SITE_KOL_006",
      "anomaly_class": "structural_crack",
      "confidence": 0.962,
      "bbox_xywh": [
        209,
        102,
        30,
        119
      ],
      "gps": {
        "lat": 22.5726379,
        "lon": 88.3639161,
        "alt_m": 27.35
      },
      "ir_temp_delta_c": 7.7,
      "inspection_phase": "antenna_inspection",
      "drone_alt_m": 45.71,
      "distance_to_tower_m": 3.52
    },
    {
      "frame_id": 690,
      "timestamp_utc": "2024-04-04T17:20:09.000Z",
      "mission_id": "MISSION_0065",
      "site_id": "SITE_KOL_006",
      "anomaly_class": "structural_crack",
      "confidence": 0.878,
      "bbox_xywh": [
        209,
        102,
        30,
        119
      ],
      "gps": {
        "lat": 22.5726379,
        "lon": 88.3639161,
        "alt_m": 27.35
      },
      "ir_temp_delta_c": 6.7,
      "inspection_phase": "antenna_inspection",
      "drone_alt_m": 45.69,
      "distance_to_tower_m": 3.09
    },
    {
      "frame_id": 691,
      "timestamp_utc": "2024-04-04T17:20:09.100Z",
      "mission_id": "MISSION_0065",
      "site_id": "SITE_KOL_006",
      "anomaly_class": "structural_crack",
      "confidence": 0.898,
      "bbox_xywh": [
        209,
        102,
        30,
        119
      ],
      "gps": {
        "lat": 22.5726379,
        "lon": 88.3639161,
        "alt_m": 27.35
      },
      "ir_temp_delta_c": 7.8,
      "inspection_phase": "antenna_inspection",
      "drone_alt_m": 45.73,
      "distance_to_tower_m": 2.62
    },
    {
      "frame_id": 692,
      "timestamp_utc": "2024-04-04T17:20:09.200Z",
      "mission_id": "MISSION_0065",
      "site_id": "SITE_KOL_006",
      "anomaly_class": "structural_crack",
      "confidence": 0.916,
      "bbox_xywh": [
        209,
        102,
        30,
        119
      ],
      "gps": {
        "lat": 22.5726379,
        "lon": 88.3639161,
        "alt_m": 27.35
      },
      "ir_temp_delta_c": 4.4,
      "inspection_phase": "antenna_inspection",
      "drone_alt_m": 45.73,
      "distance_to_tower_m": 2.62
    },
    {
      "frame_id": 693,
      "timestamp_utc": "2024-04-04T17:20:09.300Z",
      "mission_id": "MISSION_0065",
      "site_id": "SITE_KOL_006",
      "anomaly_class": "structural_crack",
      "confidence": 0.921,
      "bbox_xywh": [
        209,
        102,
        30,
        119
      ],
      "gps": {
        "lat": 22.5726379,
        "lon": 88.3639161,
        "alt_m": 27.35
      },
      "ir_temp_delta_c": 8.5,
      "inspection_phase": "antenna_inspection",
      "drone_alt_m": 45.75,
      "distance_to_tower_m": 3.0
    },
    {
      "frame_id": 694,
      "timestamp_utc": "2024-04-04T17:20:09.400Z",
      "mission_id": "MISSION_0065",
      "site_id": "SITE_KOL_006",
      "anomaly_class": "structural_crack",
      "confidence": 0.897,
      "bbox_xywh": [
        209,
        102,
        30,
        119
      ],
      "gps": {
        "lat": 22.5726379,
        "lon": 88.3639161,
        "alt_m": 27.35
      },
      "ir_temp_delta_c": 7.0,
      "inspection_phase": "antenna_inspection",
      "drone_alt_m": 45.79,
      "distance_to_tower_m": 3.49
    },
    {
      "frame_id": 695,
      "timestamp_utc": "2024-04-04T17:20:09.500Z",
      "mission_id": "MISSION_0065",
      "site_id": "SITE_KOL_006",
      "anomaly_class": "structural_crack",
      "confidence": 0.864,
      "bbox_xywh": [
        209,
        102,
        30,
        119
      ],
      "gps": {
        "lat": 22.5726379,
        "lon": 88.3639161,
        "alt_m": 27.35
      },
      "ir_temp_delta_c": 8.4,
      "inspection_phase": "antenna_inspection",
      "drone_alt_m": 45.81,
      "distance_to_tower_m": 3.59
    },
    {
      "frame_id": 696,
      "timestamp_utc": "2024-04-04T17:20:09.600Z",
      "mission_id": "MISSION_0065",
      "site_id": "SITE_KOL_006",
      "anomaly_class": "structural_crack",
      "confidence": 0.944,
      "bbox_xywh": [
        209,
        102,
        30,
        119
      ],
      "gps": {
        "lat": 22.5726379,
        "lon": 88.3639161,
        "alt_m": 27.35
      },
      "ir_temp_delta_c": 6.8,
      "inspection_phase": "antenna_inspection",
      "drone_alt_m": 45.82,
      "distance_to_tower_m": 3.79
    },
    {
      "frame_id": 697,
      "timestamp_utc": "2024-04-04T17:20:09.700Z",
      "mission_id": "MISSION_0065",
      "site_id": "SITE_KOL_006",
      "anomaly_class": "structural_crack",
      "confidence": 0.962,
      "bbox_xywh": [
        209,
        102,
        30,
        119
      ],
      "gps": {
        "lat": 22.5726379,
        "lon": 88.3639161,
        "alt_m": 27.35
      },
      "ir_temp_delta_c": 6.3,
      "inspection_phase": "antenna_inspection",
      "drone_alt_m": 45.83,
      "distance_to_tower_m": 3.75
    },
    {
      "frame_id": 698,
      "timestamp_utc": "2024-04-04T17:20:09.800Z",
      "mission_id": "MISSION_0065",
      "site_id": "SITE_KOL_006",
      "anomaly_class": "structural_crack",
      "confidence": 0.91,
      "bbox_xywh": [
        209,
        102,
        30,
        119
      ],
      "gps": {
        "lat": 22.5726379,
        "lon": 88.3639161,
        "alt_m": 27.35
      },
      "ir_temp_delta_c": 8.3,
      "inspection_phase": "antenna_inspection",
      "drone_alt_m": 45.85,
      "distance_to_tower_m": 4.01
    },
    {
      "frame_id": 699,
      "timestamp_utc": "2024-04-04T17:20:09.900Z",
      "mission_id": "MISSION_0065",
      "site_id": "SITE_KOL_006",
      "anomaly_class": "structural_crack",
      "confidence": 0.923,
      "bbox_xywh": [
        209,
        102,
        30,
        119
      ],
      "gps": {
        "lat": 22.5726379,
        "lon": 88.3639161,
        "alt_m": 27.35
      },
      "ir_temp_delta_c": 6.0,
      "inspection_phase": "antenna_inspection",
      "drone_alt_m": 45.82,
      "distance_to_tower_m": 3.92
    },
    {
      "frame_id": 700,
      "timestamp_utc": "2024-04-04T17:20:10.000Z",
      "mission_id": "MISSION_0065",
      "site_id": "SITE_KOL_006",
      "anomaly_class": "structural_crack",
      "confidence": 0.9,
      "bbox_xywh": [
        209,
        102,
        30,
        119
      ],
      "gps": {
        "lat": 22.5726379,
        "lon": 88.3639161,
        "alt_m": 27.35
      },
      "ir_temp_delta_c": 8.0,
      "inspection_phase": "antenna_inspection",
      "drone_alt_m": 45.92,
      "distance_to_tower_m": 3.54
    }
  ]
}